humanize_number
